{
  "lesson_meta": {
    "title": "இயல் 3: யார் தலைவர்? *",
    "unit": 1,
    "grade": "4",
    "term": "1",
    "subject": "Tamil",
    "code": "tam_4_t1_l3"
  },
  "material": {
    "sections": [
      {
        "title": "1. பாடச் சுருக்கம் (கதையின் முழுப் பகுதி)",
        "content": "<div style='background: #f0fdf4; border-left: 5px solid #22c55e; padding: 1.5rem; border-radius: 0.75rem; line-height: 1.8; color: #166534; font-size: 1.1rem;'><p>ஒரு காட்டின் தலைவராக <b>புலி</b> இருந்தது. அது காட்டில் உள்ள அனைவரையும் பயமுறுத்தியே அதிகாரம் செய்து வந்தது. இதனால் காட்டில் யாருக்கும் நிம்மதி இல்லை. எல்லாரும் எப்படி மகிழ்ச்சியாக வாழ்வது என்று எண்ணினர். ஒருநாள், புலி முயலிடம் வந்து, 'காட்டின் தலைவர் நான். என்னைக் கண்டால் பயமாக இல்லையா?' என்று கேட்டது. </p><p>அதற்கு முயல் தைரியமாக, 'நான் எதற்குப் பயப்பட வேண்டும்? தலைவர் என்றால் எங்களைக் காப்பவர்தானே?' என்று கேட்டது. 'நீங்கள் பயமுறுத்துகிறீர்கள், உங்களைக் கண்டு எல்லாரும் பயப்படுகிறார்கள். தலைவர் என்றால் மரியாதையும் அன்பும்தான் வரவேண்டும். உங்களை வெறுக்கிறார்கள். வேறு தலைவரைத் தேர்ந்தெடுக்கவும் முடிவெடுத்துள்ளார்கள்' என்று முயல் கூறியது. </p><p>இதைக் கேட்ட புலி, 'என்னை எல்லாரும் தலைவராக ஏற்றுக்கொள்ள நான் என்ன செய்ய வேண்டும்?' என்று கேட்டது. அதற்கு முயல், 'என்னை உங்கள் முதுகில் ஏற்றிச் செல்லுங்கள், பிறகு நடப்பதைப் பாருங்கள்' என்று கூறி புலியின் முதுகில் ஏறிச் சென்றது. </p><p>புலியின் முதுகில் சவாரி செய்தபடி வந்த முயல் விலங்குகளிடம், 'பயப்படாதீர்கள். உங்கள் குறைகளைக் கேட்க வந்திருக்கிறேன். நம்புங்கள். தலைவர் நம் மீது அன்போடு இருக்கிறார்' என்றது. புலியின் இந்த மாற்றத்தைக் கண்டு விலங்குகள் அனைத்தும் (குரங்கு, கரடி, ஒட்டகச்சிவிங்கி) வியப்படைந்தன, மகிழ்ச்சியடைந்தன. புலி முயலிடம், 'இந்தக் காடே மகிழ்ச்சியாக இருக்கிறது. அதற்குக் காரணம் நீதான்' என்றது. அதற்கு முயல், 'நீங்களும்தான் காரணம்! எங்கள் உணர்வுகளைப் புரிந்து கொண்டீர்கள்' என்றது.</p></div>"
      },
      {
        "title": "2. முக்கிய குறிப்புகள்",
        "content": "<div style='background: #fffbeb; border-left: 5px solid #f59e0b; padding: 1.5rem; border-radius: 0.75rem; color: #92400e;'><p>● ஒரு சிறந்த தலைவர் என்பவர் அதிகாரத்தாலும் பயமுறுத்தலாலும் ஆளக் கூடாது. அன்பு, பாதுகாப்பு மற்றும் மரியாதையின் மூலம் மட்டுமே சிறந்த தலைவராக உருவெடுக்க முடியும்.</p><p>● விலங்குகளின் உணர்வுகளைப் புரிந்து கொண்டதால் புலியால் சிறந்த தலைவராக மாற முடிந்தது. இக்கதை நமக்கு அதிகாரத்தை விட அன்பே சிறந்தது என்பதை உணர்த்துகிறது.</p></div>"
      },
      {
        "title": "3. மொழியோடு விளையாடு - ஒலிப்புமுறை",
        "content": "<div style='background: #f8fafc; padding: 1.5rem; border-radius: 0.75rem; border: 1px solid #e2e8f0;'><h4 style='color: #0f172a; margin-top: 0;'>ஒலிப்புமுறைக்கு ஏற்ப சொற்கள்:</h4><div style='display: grid; grid-template-columns: repeat(3, 1fr); gap: 1rem;'><div style='background: #eff6ff; padding: 1rem; border-radius: 0.5rem;'><b>'ல்' ஓசை:</b><br/>வால், பால், அகல், சொல், மல்லி, பல்லி</div><div style='background: #fdf2f8; padding: 1rem; border-radius: 0.5rem;'><b>'ள்' ஓசை:</b><br/>வாள், நாள், தோள், பள்ளி, வள்ளி, வெள்ளி</div><div style='background: #f0fdfa; padding: 1rem; border-radius: 0.5rem;'><b>'ழ்' ஓசை:</b><br/>வாழ், யாழ், மகிழ், தமிழ், புகழ், அகழ்</div></div></div>"
      },
      {
        "title": "4. அகர வரிசைப்படுத்துக",
        "content": "<div style='background: #fafaf9; border: 1px dashed #d6d3d1; padding: 1.5rem; border-radius: 0.75rem;'><p><b>அகர வரிசைப்படி அமைக்கப்பட்ட சொற்கள்:</b></p><ol style='line-height: 2; color: #44403c;'><li>பாட்டு (பா)</li><li>பின்னல் (பி)</li><li>புற்று (பு)</li><li>பூமி (பூ)</li><li>பெட்டி (பெ)</li><li>பை (பை)</li><li>பொறி (பொ)</li><li>பௌவம் (பௌ)</li></ol></div>"
      },
      {
        "title": "5. ஈரெழுத்துச் சொற்கள் (மைய எழுத்து 'ர்')",
        "content": "<div style='display: grid; grid-template-columns: repeat(auto-fit, minmax(200px, 1fr)); gap: 0.75rem;'><div style='background: #f1f5f9; padding: 0.75rem; border-radius: 0.5rem;'>உலகம் - <b>பார்</b></div><div style='background: #f1f5f9; padding: 0.75rem; border-radius: 0.5rem;'>திருவிழா - <b>தேர்</b></div><div style='background: #f1f5f9; padding: 0.75rem; border-radius: 0.5rem;'>மக்கள் வாழுமிடம் - <b>ஊர்</b></div><div style='background: #f1f5f9; padding: 0.75rem; border-radius: 0.5rem;'>உயிர் நீர் - <b>நீர்</b></div><div style='background: #f1f5f9; padding: 0.75rem; border-radius: 0.5rem;'>தயிர் - <b>மோர்</b></div><div style='background: #f1f5f9; padding: 0.75rem; border-radius: 0.5rem;'>தாவரம் - <b>வேர்</b></div><div style='background: #f1f5f9; padding: 0.75rem; border-radius: 0.5rem;'>பூத்தொடுக்க - <b>நார்</b></div></div>"
      },
      {
        "title": "6. மதிப்பீட்டு வினாக்கள்",
        "content": "<div style='background: #fef2f2; padding: 1.5rem; border-radius: 0.75rem; border: 1px solid #fee2e2;'><p>1. <b>குறை:</b> எதிர்ச்சொல் - <b>நிறை</b></p><p>2. <b>இப்போதெல்லாம்:</b> இப்போது + எல்லாம்</p><p>3. <b>முடியவில்லையே:</b> முடிய + இல்லையே</p><p>4. <b>தேர்ந்தெடுக்க:</b> தேர்ந்து + எடுக்க</p></div>"
      },
      {
        "title": "7. வினாக்களுக்கு விடையளிக்க",
        "content": "<div style='background: #fdf4ff; padding: 1.5rem; border-radius: 0.75rem; border: 1px solid #fae8ff;'><p style='font-weight: bold;'>1. முயல் எதைப் பற்றிச் சிந்தித்தது?</p><p>விடை: காட்டில் உள்ள விலங்குகள் அனைத்தும் புலியைக் கண்டு பயப்படாமல் எப்படி மகிழ்ச்சியாகவும் நிம்மதியாகவும் வாழ்வது என்பதைப் பற்றிச் சிந்தித்தது.</p><p style='font-weight: bold; margin-top: 1rem;'>2. காட்டில் விலங்குகள் அனைத்தும் மகிழ்ச்சியாக இருக்கக் காரணம் என்ன?</p><p>விடை: காட்டின் தலைவரான புலி, தன் அதிகாரத்தையும் பயமுறுத்தும் குணத்தையும் மாற்றி, விலங்குகளின் உணர்வுகளைப் புரிந்து கொண்டு அன்பான தலைவராக மாறியதே காரணமாகும்.</p></div>"
      }
    ]
  },
  "quiz": {
    "questions": [
      {
        "question": "காட்டின் தலைவராக அதிகாரம் செய்து வந்தது எந்த விலங்கு?",
        "options": ["சிங்கம்", "புலி", "யானை", "கரடி"],
        "answer": 1,
        "explanation": "கதையின் தொடக்கத்தில் புலியே காட்டின் தலைவராக இருந்து அனைவரையும் பயமுறுத்தி வந்தது."
      },
      {
        "question": "புலியின் ஆட்சியால் காட்டில் உள்ள விலங்குகளின் நிலை என்னவாக இருந்தது?",
        "options": ["மிகவும் மகிழ்ச்சியாக இருந்தன", "யாருக்கும் நிம்மதி இல்லை", "அமைதியாக தூங்கின", "புலியுடன் சேர்ந்து வேட்டையாடின"],
        "answer": 1,
        "explanation": "புலி அனைவரையும் பயமுறுத்தியதால் காட்டில் யாருக்கும் நிம்மதி இல்லை என்று பாடப்பகுதி கூறுகிறது."
      },
      {
        "question": "தலைவர் என்றால் எப்படி இருக்க வேண்டும் என்று முயல் புலியிடம் கூறியது?",
        "options": ["எல்லாரையும் பயமுறுத்த வேண்டும்", "மரியாதையும் அன்பும் கொண்டவராக வர வேண்டும்", "எப்போதும் தூங்கிக் கொண்டே இருக்க வேண்டும்", "தனியாக வாழ வேண்டும்"],
        "answer": 1,
        "explanation": "தலைவர் என்றால் மரியாதையும் அன்பும் தான் வர வேண்டும், பயம் வரக்கூடாது என்று முயல் தைரியமாகக் கூறியது."
      },
      {
        "question": "புலியிடம் காட்டில் உள்ள விலங்குகள் என்ன முடிவெடுத்துள்ளதாக முயல் கூறியது?",
        "options": ["காட்டை விட்டு வெளியேற முடிவெடுத்துள்ளன", "புலியைக் கொல்ல முடிவெடுத்துள்ளன", "வேறு தலைவரைத் தேர்ந்தெடுக்க முடிவெடுத்துள்ளன", "புலியுடன் சமாதானம் செய்ய முடிவெடுத்துள்ளன"],
        "answer": 2,
        "explanation": "புலியை அனைவரும் வெறுப்பதால் வேறு தலைவரைத் தேர்ந்தெடுக்க முடிவெடுத்துள்ளதாக முயல் தந்திரமாகக் கூறியது."
      },
      {
        "question": "தன்னைத் தலைவராக ஏற்றுக்கொள்ளச் செய்ய புலி என்ன செய்ய வேண்டும் என்று முயல் ஆலோசனை கூறியது?",
        "options": ["தன்னை முதுகில் ஏற்றிச் செல்ல வேண்டும்", "அனைவருக்கும் உணவு தர வேண்டும்", "காட்டை விட்டுப் போக வேண்டும்", "முயலுக்கு மணிமகுடம் தர வேண்டும்"],
        "answer": 0,
        "explanation": "என்னை உங்கள் முதுகில் ஏற்றிச் செல்லுங்கள், பிறகு நடப்பதைப் பாருங்கள் என்று முயல் புலியிடம் கூறியது."
      },
      {
        "question": "புலியின் முதுகில் சவாரி செய்தபடி வந்த முயல் மற்ற விலங்குகளிடம் என்ன கூறியது?",
        "options": ["நான் தான் புதிய தலைவர்", "உங்கள் குறைகளைக் கேட்க வந்திருக்கிறேன்", "புலி எனக்கு அடிமையாகிவிட்டது", "நீங்கள் அனைவரும் இங்கிருந்து ஓடிவிடுங்கள்"],
        "answer": 1,
        "explanation": "பயப்படாதீர்கள், உங்கள் குறைகளைக் கேட்க வந்திருக்கிறேன், தலைவர் நம் மீது அன்போடு இருக்கிறார் என்று முயல் கூறியது."
      },
      {
        "question": "புலியின் முதுகில் முயல் வருவதைக் கண்ட விலங்குகளின் மனநிலை எவ்வாறு மாறியது?",
        "options": ["மேலும் பயந்தன", "கோபமடைந்தன", "வியப்படைந்து மகிழ்ச்சி அடைந்தன", "அங்கிருந்து ஓடிவிட்டன"],
        "answer": 2,
        "explanation": "இது என்ன மாற்றம், நம்ப முடியவில்லையே என்று கூறி விலங்குகள் மகிழ்ச்சியாக வந்தன."
      },
      {
        "question": "காடு மகிழ்ச்சியாக இருப்பதற்கு யார் காரணம் என்று புலி கூறியது?",
        "options": ["கரடி", "முயல்", "குரங்கு", "ஒட்டகச்சிவிங்கி"],
        "answer": 1,
        "explanation": "இந்தக் காடே மகிழ்ச்சியாக இருக்கிறது, அதற்குக் காரணம் நீதான் என்று புலி முயலிடம் கூறியது."
      },
      {
        "question": "காடு மகிழ்ச்சியாக இருப்பதற்கு யார் காரணம் என்று முயல் திருப்பிச் சொன்னது?",
        "options": ["புலி", "தன்னுடைய புத்திசாலித்தனம்", "இயற்கை", "மற்ற விலங்குகள்"],
        "answer": 0,
        "explanation": "நீங்களும்தான் காரணம்! எங்கள் உணர்வுகளைப் புரிந்து கொண்டீர்கள் என்று முயல் புலியிடம் கூறியது."
      },
      {
        "question": "கதையின் முடிவில் முயலின் செயல்பாடு என்ன?",
        "options": ["காட்டின் தலைவரானது", "வயிறு நிரம்பச் சாப்பிட்டு நிம்மதியாகத் தூங்கியது", "புலியிடம் சண்டை போட்டது", "காட்டை விட்டுச் சென்றது"],
        "answer": 1,
        "explanation": "இப்போதெல்லாம் வயிறு நிரம்பச் சாப்பிட்டு நிம்மதியாகக் குட்டித் தூக்கமும் போடுகிறது முயல் என கதை முடிகிறது."
      },
      {
        "question": "குறை - இச்சொல்லின் எதிர்ச்சொல் என்ன?",
        "options": ["தீமை", "தவறு", "நிறை", "நிறைவு"],
        "answer": 2,
        "explanation": "குறை என்பதன் சரியான எதிர்ச்சொல் நிறை என்பதாகும்."
      },
      {
        "question": "இப்போதெல்லாம் - இச்சொல்லைப் பிரித்து எழுதக் கிடைப்பது எது?",
        "options": ["இப்போது + தெல்லாம்", "இப்போ + தெல்லாம்", "இப்போ + துல்லாம்", "இப்போது + எல்லாம்"],
        "answer": 3,
        "explanation": "இப்போது + எல்லாம் சேரும்போது உகரம் கெட்டு 'இப்போதெல்லாம்' என ஆகும்."
      },
      {
        "question": "முடிய + இல்லையே என்பதைச் சேர்த்து எழுதக் கிடைக்கும் சொல் எது?",
        "options": ["முடியலையே", "முடியவில்லையே", "முடிவில்லையே", "முடியயவில்லையே"],
        "answer": 1,
        "explanation": "முடிய + இல்லையே சேரும்போது வகர உடம்படுமெய் தோன்றி 'முடியவில்லையே' என ஆகும்."
      },
      {
        "question": "தேர்ந்து + எடுக்க என்பதைச் சேர்த்து எழுதக் கிடைக்கும் சொல் எது?",
        "options": ["தேர்ந்தெடுக்க", "தேர்ந்ததெடுக்க", "தேர்ந்துஎடுக்க", "தேர்ந்துடுக்க"],
        "answer": 0,
        "explanation": "தேர்ந்து + எடுக்க புணரும்போது உகரம் கெட்டு 'தேர்ந்தெடுக்க' என புணரும்."
      },
      {
        "question": "கீழ்க்காணும் சொற்களுள் 'ல்' (சிறு ல்) ஓசை கொண்ட சொல் எது?",
        "options": ["வாள்", "மகிழ்", "மல்லி", "வள்ளி"],
        "answer": 2,
        "explanation": "வாள்(ள்), மகிழ்(ழ்), வள்ளி(ள்). மல்லி என்பது மட்டுமே 'ல்' ஓசை கொண்ட சொல்."
      },
      {
        "question": "கீழ்க்காணும் சொற்களுள் 'ள்' (பெரிய ள்) ஓசை கொண்ட சொல் எது?",
        "options": ["பல்லி", "பள்ளி", "தமிழ்", "பால்"],
        "answer": 1,
        "explanation": "பல்லி(ல்), தமிழ்(ழ்), பால்(ல்). பள்ளி என்பது மட்டுமே 'ள்' ஓசை கொண்ட சொல்."
      },
      {
        "question": "கீழ்க்காணும் சொற்களுள் 'ழ்' (சிறப்பு ழ்) ஓசை கொண்ட சொல் எது?",
        "options": ["அகல்", "தோள்", "புகழ்", "வெள்ளி"],
        "answer": 2,
        "explanation": "அகல்(ல்), தோள்(ள்), வெள்ளி(ள்). புகழ் என்பது மட்டுமே 'ழ்' ஓசை கொண்ட சொல்."
      },
      {
        "question": "பொருந்தாத இணையைத் தேர்ந்தெடுக்க.",
        "options": ["வால் - ல்", "பள்ளி - ள்", "தமிழ் - ழ்", "நாள் - ல்"],
        "answer": 3,
        "explanation": "நாள் என்ற சொல் 'ள்' ஓசையில் முடிவடைகிறது, 'ல்' ஓசையில் அல்ல."
      },
      {
        "question": "அகர வரிசைப்படி அமைக்கப்பட்ட சரியான வரிசையைத் தேர்ந்தெடுக்க.",
        "options": ["பெட்டி, பை, பூமி", "பாட்டு, பின்னல், புற்று", "பொறி, பௌவம், பை", "புற்று, பூமி, பாட்டு"],
        "answer": 1,
        "explanation": "'ப' வரிசைப்படி பா, பி, பு என்ற வரிசை சரியானது."
      },
      {
        "question": "'பூமி, பை, பெட்டி, பாட்டு' - இச்சொற்களை அகர வரிசைப்படுத்தினால் முதலாவதாக வரும் சொல் எது?",
        "options": ["பூமி", "பை", "பெட்டி", "பாட்டு"],
        "answer": 3,
        "explanation": "பா, பி, பு, பூ, பெ, பே, பை என்ற வரிசையில் 'பா' எழுத்தில் தொடங்கும் பாட்டு முதலாவதாக வரும்."
      },
      {
        "question": "'பின்னல்' என்ற சொல்லுக்கு அகர வரிசைப்படி அடுத்து வரும் சொல் எது?",
        "options": ["பூமி", "புற்று", "பை", "பொறி"],
        "answer": 1,
        "explanation": "'பி' எழுத்துக்குப் பிறகு 'பு' எழுத்து வர வேண்டும். எனவே பின்னல் என்பதற்கு அடுத்து புற்று வரும்."
      },
      {
        "question": "'பௌவம்' என்ற சொல் 'ப' வரிசை அகர வரிசையில் எத்தனையாவது இடத்தில் இடம்பெறும்?",
        "options": ["முதலாவது", "எட்டாவது", "நான்காவது", "பன்னிரண்டாவது"],
        "answer": 3,
        "explanation": "'ப' வரிசையில் (ப, பா, பி, பீ, பு, பூ, பெ, பே, பை, பொ, போ, பௌ) 'பௌவம்' (பௌ) என்பது 12-வது இடத்தைப் பெறும்."
      },
      {
        "question": "உலகம் என்பதன் வேறு சொல் (ஈரெழுத்துச் சொல்) என்ன?",
        "options": ["தேர்", "நீர்", "பார்", "ஊர்"],
        "answer": 2,
        "explanation": "உலகம் என்பதைக் குறிக்கும் ஈரெழுத்துச் சொல் 'பார்' (பா + ர்)."
      },
      {
        "question": "திருவிழா என்றால் இது இருக்கும். குறிப்பைக் கொண்டு ஈரெழுத்துச் சொல்லைக் கண்டறிக.",
        "options": ["மோர்", "தேர்", "வேர்", "நார்"],
        "answer": 1,
        "explanation": "திருவிழாக்களில் முக்கியமாக இடம்பெறுவது தேர் (தே + ர்)."
      },
      {
        "question": "மக்கள் வாழுமிடம் எது? (ஈரெழுத்துச் சொல்)",
        "options": ["நீர்", "ஊர்", "பார்", "காடு"],
        "answer": 1,
        "explanation": "மக்கள் வாழும் இடத்தை 'ஊர்' (ஊ + ர்) என்று அழைப்பர்."
      },
      {
        "question": "இது இல்லாமல் உயிர்கள் இல்லை - குறிப்பு உணர்த்தும் சொல் எது?",
        "options": ["வேர்", "மோர்", "பார்", "நீர்"],
        "answer": 3,
        "explanation": "நீரின்றி அமையாது உலகு. நீர் (நீ + ர்) இல்லாமல் உயிர்கள் வாழ முடியாது."
      },
      {
        "question": "தயிரைக் கடைந்தால் கிடைப்பது எது?",
        "options": ["மோர்", "பால்", "நெய்", "வெண்ணெய்"],
        "answer": 0,
        "explanation": "ஈரெழுத்துச் சொற்கள் குறிப்பின்படி, தயிரைக் கடைந்தால் கிடைப்பது மோர் (மோ + ர்)."
      },
      {
        "question": "தாவரங்கள் மண்ணில் ஊன்றி நிற்க உதவுவது எது?",
        "options": ["கிளை", "இலை", "வேர்", "தண்டு"],
        "answer": 2,
        "explanation": "தாவரங்கள் மண்ணில் உறுதியாக நிற்க வேர் (வே + ர்) உதவுகிறது."
      },
      {
        "question": "பூத்தொடுக்கப் பயன்படுவது எது?",
        "options": ["ஊசி", "நூல்", "நார்", "கயிறு"],
        "answer": 2,
        "explanation": "பூக்களை மாலையாகத் தொடுக்க நார் (நா + ர்) பயன்படுகிறது."
      },
      {
        "question": "ஒப்புமை காண்க: புலி : பயமுறுத்தல் :: முயல் : ?",
        "options": ["வேட்டையாடுதல்", "புத்திசாலித்தனம்", "தூங்குதல்", "பயந்து ஓடுதல்"],
        "answer": 1,
        "explanation": "புலி பயமுறுத்தி ஆண்டதுபோல, முயல் தனது புத்திசாலித்தனத்தால் காட்டின் நிலையை மாற்றியது."
      },
      {
        "question": "கூற்று: காட்டில் உள்ள விலங்குகள் அனைத்தும் முயலின் செயலைக் கண்டு மகிழ்ச்சி அடைந்தன. \nகாரணம்: காட்டின் தலைவரான புலி தன் அதிகார தோரணையை மாற்றி அன்பானவராக மாறியதால்.",
        "options": ["கூற்று சரி, காரணம் தவறு", "கூற்று தவறு, காரணம் சரி", "கூற்றும் காரணமும் சரி", "கூற்றும் காரணமும் தவறு"],
        "answer": 2,
        "explanation": "புலி தனது முரட்டு குணத்தை மாற்றி அன்பான தலைவராக மாறியதாலேயே விலங்குகள் மகிழ்ச்சி அடைந்தன."
      },
      {
        "question": "பொருத்துக: \n1. வால் - அ. சிறப்பு ழகரம் \n2. வாள் - ஆ. மேல்நோக்கு லகரம் \n3. யாழ் - இ. பொது ளகரம்",
        "options": ["1-ஆ, 2-இ, 3-அ", "1-அ, 2-ஆ, 3-இ", "1-இ, 2-அ, 3-ஆ", "1-ஆ, 2-அ, 3-இ"],
        "answer": 0,
        "explanation": "வால் (ல் - மேல்நோக்கு), வாள் (ள் - பொது), யாழ் (ழ் - சிறப்பு)."
      },
      {
        "question": "கீழ்க்கண்டவற்றுள் பொருந்தாத ஒன்றைத் தேர்ந்தெடுக்க.",
        "options": ["பால்", "அகல்", "சொல்", "வாள்"],
        "answer": 3,
        "explanation": "பால், அகல், சொல் ஆகிய மூன்றும் 'ல்' முடிபைக் கொண்டவை. வாள் மட்டும் 'ள்' முடிபைக் கொண்டது."
      },
      {
        "question": "கீழ்க்கண்டவற்றுள் பொருந்தாத ஒன்றைத் தேர்ந்தெடுக்க.",
        "options": ["தமிழ்", "புகழ்", "மகிழ்", "பள்ளி"],
        "answer": 3,
        "explanation": "தமிழ், புகழ், மகிழ் ஆகிய மூன்றும் 'ழ்' முடிபைக் கொண்டவை. பள்ளி மட்டும் 'ள்' முடிபைக் கொண்டது."
      },
      {
        "question": "பொருத்துக: \n1. மக்கள் வாழுமிடம் - அ. நீர் \n2. திருவிழாவில் இருப்பது - ஆ. ஊர் \n3. உயிர் வாழ தேவையானது - இ. தேர்",
        "options": ["1-ஆ, 2-இ, 3-அ", "1-அ, 2-ஆ, 3-இ", "1-இ, 2-அ, 3-ஆ", "1-ஆ, 2-அ, 3-இ"],
        "answer": 0,
        "explanation": "மக்கள் வாழுமிடம் ஊர், திருவிழாவில் இருப்பது தேர், உயிர் வாழ தேவையானது நீர்."
      },
      {
        "question": "புலியிடம் முயல் பேசும்போது பயன்படுத்திய தொணி எவ்வாறு இருந்தது?",
        "options": ["மிகவும் பயந்து", "கெஞ்சும் குரலில்", "தைரியமாக மற்றும் தந்திரமாக", "கோபமாக கத்தியபடி"],
        "answer": 2,
        "explanation": "புலியைக் கண்டு சற்றும் அஞ்சாமல் தைரியமாகவும் தந்திரமாகவும் பேசியது."
      },
      {
        "question": "புலிக்குத் தான் ஒரு கெட்ட தலைவர் என்ற உண்மையை உணர்த்தியது எது?",
        "options": ["முயலின் தைரியமான வார்த்தைகள்", "காட்டில் உள்ள மற்ற விலங்குகளின் போராட்டம்", "வேடனின் வலை", "புலியின் சொந்த சிந்தனை"],
        "answer": 0,
        "explanation": "முயல் மட்டுமே தைரியமாக முன்வந்து விலங்குகள் புலியை வெறுக்கின்றன என்ற உண்மையை உணர்த்தியது."
      },
      {
        "question": "கூற்று: ஒரு தலைவர் எப்போதும் பிறரை பயமுறுத்தி வைத்திருக்க வேண்டும். \nகாரணம்: பயம் இருந்தால் மட்டுமே அனைவரும் சொல்வதைக் கேட்பார்கள்.",
        "options": ["கூற்றும் காரணமும் சரி", "கூற்றும் காரணமும் தவறு", "கூற்று சரி, காரணம் தவறு", "கூற்று தவறு, காரணம் சரி"],
        "answer": 1,
        "explanation": "தலைவர் என்பவர் அன்பாலும் மரியாதையாலும் ஆள வேண்டும். பயமுறுத்துதல் தவறான தலைமையின் அடையாளம்."
      },
      {
        "question": "'நான் எதற்குப் பயப்பட வேண்டும்? தலைவர் என்றால் எங்களைக் காப்பவர்தானே?' - இது யாருடைய கூற்று?",
        "options": ["குரங்கு", "கரடி", "முயல்", "புலி"],
        "answer": 2,
        "explanation": "புலி தன்னைக்கண்டு பயப்படவில்லையா என்று கேட்டபோது முயல் கூறிய பதிலாகும் இது."
      },
      {
        "question": "ஒப்புமை காண்க: பூமி : பாட்டு :: பெட்டி : ?",
        "options": ["பின்னல்", "பை", "பொறி", "புற்று"],
        "answer": 1,
        "explanation": "அகர வரிசையில் பூமி(பூ) க்கு முன் பாட்டு(பா) வருகிறது. அதுபோல பெட்டி(பெ) க்கு அடுத்து பை(பை) வருகிறது."
      },
      {
        "question": "'உண்மையான தலைவர் எப்படி இருக்க வேண்டும்' என்பதை இக்கதை மூலம் நாம் எவ்வாறு அறிகிறோம்?",
        "options": ["வலிமையானவராக இருக்க வேண்டும்", "உணர்வுகளைப் புரிந்து அன்பானவராக இருக்க வேண்டும்", "அனைவரையும் தண்டிப்பவராக இருக்க வேண்டும்", "யாரையும் பொருட்படுத்தக் கூடாது"],
        "answer": 1,
        "explanation": "புலி விலங்குகளின் உணர்வுகளைப் புரிந்து அன்பான தலைவராக மாறியதே காட்டின் மகிழ்ச்சிக்குக் காரணம்."
      },
      {
        "question": "'ல், ள், ழ்' ஆகிய எழுத்துக்களைக் கொண்டு முடியும் சொற்களைக் கற்பதன் முக்கிய நோக்கம் என்ன?",
        "options": ["கதையை எளிதாகப் புரிந்து கொள்ள", "எழுத்துக்களின் சரியான ஒலிப்பு முறையை (உச்சரிப்பை) அறிய", "வேகமாக எழுத", "பாடல் பாட"],
        "answer": 1,
        "explanation": "மொழியில் உள்ள லகர, ளகர, ழகர வேறுபாடுகளை ஒலிப்பு முறைக்கு ஏற்ப உச்சரிக்கப் பழகுவதே இதன் நோக்கமாகும்."
      },
      {
        "question": "அகர வரிசைப்படி அமைக்கப்பட்டதில் தவறான வரிசையைக் கண்டறிக.",
        "options": ["பாட்டு, பின்னல், புற்று", "பூமி, பெட்டி, பை", "பொறி, பௌவம்", "பை, பெட்டி, பூமி"],
        "answer": 3,
        "explanation": "'பை, பெட்டி, பூமி' என்பது பின்நோக்கிய வரிசை. சரியான அகர வரிசை பூமி, பெட்டி, பை என்பதாகும்."
      },
      {
        "question": "'ர்' என்ற மைய எழுத்தைக் கொண்டு உருவாக்க முடியாத சொல் எது?",
        "options": ["கார்", "ஊர்", "பார்", "நீர்"],
        "answer": 0,
        "explanation": "பாடப்பகுதியில் மற்றும் குறிப்புகளில் கார் என்ற சொல் பயிற்றுவிக்கப்படவில்லை."
      },
      {
        "question": "முயல் புலியின் முதுகில் ஏறிச் சென்றபோது மற்ற விலங்குகளின் நிலை என்ன?",
        "options": ["பயத்தில் ஒளிந்து கொண்டன", "ஆச்சரியத்தில் உறைந்து போய் மகிழ்ச்சி அடைந்தன", "முயலைக் காப்பாற்ற ஓடி வந்தன", "புலியைக் கண்டு சிரித்தன"],
        "answer": 1,
        "explanation": "புலி மாறிவிட்டதைக் கண்டு விலங்குகள் ஆச்சரியமும் மகிழ்ச்சியும் அடைந்தன."
      },
      {
        "question": "புலி முயலின் பேச்சைக் கேட்டுத் தன்னை மாற்றிக் கொள்ள முக்கிய காரணம் என்னவாக இருக்கலாம்?",
        "options": ["முயல் தன்னை விட வலிமையானது என்ற பயம்", "யாரும் தன்னைத் தலைவராக மதிக்கவில்லை என்ற உண்மையை உணர்ந்ததால்", "முயல் தன்னிடம் உணவு கொடுத்ததால்", "காட்டை விட்டுத் துரத்தி விடுவார்கள் என்ற பயத்தால்"],
        "answer": 1,
        "explanation": "தன் மீது எவருக்கும் மரியாதை இல்லை என்பதை உணர்ந்ததே அதன் மாற்றத்திற்குக் காரணம்."
      },
      {
        "question": "'நீங்கள் பயமுறுத்துகிறீர்கள். உங்களைக் கண்டு எல்லாரும் பயப்படுகிறார்கள்' என்று முயல் புலியிடம் நேரடியாகக் கூற என்ன பண்பு தேவை?",
        "options": ["கோபம்", "அறியாமை", "துணிச்சல் மற்றும் தலைமைப் பண்பு", "பொறாமை"],
        "answer": 2,
        "explanation": "ஆபத்தான விலங்கிடம் உண்மையை தைரியமாகப் பேச துணிச்சலும் மற்றவர்களுக்கான பொறுப்பும் தேவை."
      },
      {
        "question": "புலியின் முதுகில் ஏறி முயல் வருவதைப் பார்த்த விலங்குகள், 'இதைத்தான் எதிர்பார்த்தோம்' என்று கூறக் காரணம் என்ன?",
        "options": ["முயல் காட்டின் தலைவராக வேண்டும் என்று", "தலைவர் அனைவரிடமும் அன்போடும் சகஜமாகவும் பழக வேண்டும் என்று", "புலிக்குத் தண்டனை கிடைக்க வேண்டும் என்று", "முயல் புலியைக் கொன்றுவிடும் என்று"],
        "answer": 1,
        "explanation": "தலைவர் அன்பாகப் பழக வேண்டும் என்பதையே விலங்குகள் எதிர்பார்த்தன."
      },
      {
        "question": "உங்கள் வகுப்பில் ஒரு மாணவர் மற்றவர்களைப் பயமுறுத்தித் தலைவனாக இருக்க நினைக்கிறார். நீங்கள் என்ன செய்வீர்கள்?",
        "options": ["பயந்து அவர் சொல்வதைக் கேட்பேன்", "அவரிடம் சண்டை போடுவேன்", "தைரியமாகச் சென்று அன்பால் மட்டுமே சிறந்த தலைவராக முடியும் என்று புரியவைப்பேன்", "அமைதியாக இருப்பேன்"],
        "answer": 2,
        "explanation": "தவறான செயலை தைரியமாகச் சுட்டிக்காட்டி சரியான வழியைப் புரிய வைப்பதே சிறந்த பண்பாகும்."
      },
      {
        "question": "இக்கதையின் மூலம் நீ அறிந்துகொள்ளும் மிக முக்கியமான அறநெறி என்ன?",
        "options": ["வலிமையுள்ளவனே வெற்றி பெறுவான்", "அதிகாரத்தால் அல்ல, அன்பால் மட்டுமே உண்மையான தலைவனாக முடியும்", "எப்போதும் தந்திரமாக இருக்க வேண்டும்", "விலங்குகள் ஒன்றாக வாழ முடியாது"],
        "answer": 1,
        "explanation": "உண்மையான தலைமை என்பது பயமுறுத்தலில் இல்லை, அனைவரையும் நேசிப்பதில்தான் உள்ளது."
      }
    ]
  }
}
